Workbook
Name JJJ: PIVOT_CATAGORY!$A$3

Sheet customers
A1: customer_id | B1: customer_name | C1: address | D1: customer_type | E1: created_date
A2: CUST0001 | B2: Devi | C2: Anna Nagar, Thanjavur | D2: New | E2: 45426
A3: CUST0002 | B3: Poongothai | C3: Mariamman Kovil Street, Thanjavur | D3: New | E3: 45618
A4: CUST0003 | B4: Indhu | C4: Railway Station, Thanjavur | D4: Regular | E4: 45589
A5: CUST0004 | B5: Anu | C5: Indira Nagar, Thanjavur | D5: Regular | E5: 45625
A6: CUST0005 | B6: Mahesh Chidambaram | C6: Vannarapettai, Thanjavur | D6: Premium | E6: 45415
A7: CUST0006 | B7: Devi | C7: Old Housing Unit, Thanjavur | D7: Regular | E7: 45503
A8: CUST0007 | B8: Sangeetha | C8: Railway Station, Thanjavur | D8: New | E8: 45693
A9: CUST0008 | B9: Saravanan | C9: Anna Nagar, Thanjavur | D9: Regular | E9: 45679
A10: CUST0009 | B10: Ulagam | C10: Big Bazaar Street, Thanjavur | D10: Regular | E10: 45601
A11: CUST0010 | B11: Chandrasekar | C11: Ayyampettai, Thanjavur | D11: New | E11: 45742
A12: CUST0011 | B12: Nagalakshmi | C12: Thiruvaiyaru, Thanjavur | D12: New | E12: 45541
A13: CUST0012 | B13: Durga | C13: Thiruvaiyaru, Thanjavur | D13: New | E13: 45642
... A488: CUST0487 | B488: Ravi Kumar | C488: New Housing Unit, Thanjavur | D488: Regular | E488: 45660

Sheet Sheet5
A3: Row Labels | B3: Count of order_id | C3: Sum of total_amount | D3: Sum of discount | E3: Sum of final_amount | F3: CANCELATION RATE
A4: Cancelled | B4: 142 | C4: 74614 | D4: 2055.25 | E4: 0 | F4: =B4/B6 -> 0.077006508
A5: Delivered | B5: 1702 | C5: 891440 | D5: 22478.6 | E5: 868961.4 | F5: =B5/B6 -> 0.92299349
A6: Grand Total | B6: 1844 | C6: 966054 | D6: 24533.85 | E6: 868961.4

Sheet MONTH REVENUE
A3: Row Labels | B3: Sum of final_amount
A4: 2024 | B4: 668408.1
A5: Apr | B5: 65053.75
A6: May | B6: 67918.55
A7: Jun | B7: 51122.6
A8: Jul | B8: 64294.5
A9: Aug | B9: 69161.95
A10: Sep | B10: 67412.25
A11: Oct | B11: 81170.55
A12: Nov | B12: 104728.45
A13: Dec | B13: 97545.5
A14: 2025 | B14: 200553.3
A15: Jan | B15: 75576.25
... A18: Grand Total | B18: 868961.4

Sheet orders
A1: order_id | B1: customer_id | C1: order_channel | D1: order_date | E1: order_time | F1: order_status | G1: total_amount | H1: discount | I1: final_amount | J1: check_total | K1: CUSTOMER_TYPE
A2: ORD6443037 | B2: CUST0182 | C2: Swiggy | D2: 45596 | E2: 0.67013889 | F2: Delivered | G2: 207 | H2: 0 | I2: 207 | J2: =SUMIF(order_item!B:B,A2,order_item!E:E) -> 207 | K2: =_xlfn.XLOOKUP(B2,customers!A:A,customers!D:D) -> New
A3: ORD7387623 | B3: CUST0267 | C3: Zomato | D3: 45598 | E3: 0.525 | F3: Delivered | G3: 238 | H3: 0 | I3: 238 | J3: =SUMIF(order_item!B:B,A3,order_item!E:E) -> 238 | K3: =_xlfn.XLOOKUP(B3,customers!A:A,customers!D:D) -> Regular
A4: ORD4280754 | B4: CUST0370 | C4: Swiggy | D4: 45576 | E4: 0.76041667 | F4: Delivered | G4: 356 | H4: 0 | I4: 356 | J4: =SUMIF(order_item!B:B,A4,order_item!E:E) -> 356 | K4: =_xlfn.XLOOKUP(B4,customers!A:A,customers!D:D) -> Premium
A5: ORD3283789 | B5: CUST0172 | C5: Zomato | D5: 45615 | E5: 0.60277778 | F5: Delivered | G5: 484 | H5: 0 | I5: 484 | J5: =SUMIF(order_item!B:B,A5,order_item!E:E) -> 484 | K5: =_xlfn.XLOOKUP(B5,customers!A:A,customers!D:D) -> New
A6: ORD7309161 | B6: CUST0401 | C6: Zomato | D6: 45505 | E6: 0.94166667 | F6: Delivered | G6: 1010 | H6: 0 | I6: 1010 | J6: =SUMIF(order_item!B:B,A6,order_item!E:E) -> 1010 | K6: =_xlfn.XLOOKUP(B6,customers!A:A,customers!D:D) -> Premium
A7: ORD7864256 | B7: CUST0355 | C7: Zomato | D7: 45641 | E7: 0.78680556 | F7: Delivered | G7: 188 | H7: 18.8 | I7: 169.2 | J7: =SUMIF(order_item!B:B,A7,order_item!E:E) -> 188 | K7: =_xlfn.XLOOKUP(B7,customers!A:A,customers!D:D) -> Regular
A8: ORD8017921 | B8: CUST0206 | C8: Swiggy | D8: 45411 | E8: 0.94236111 | F8: Delivered | G8: 158 | H8: 0 | I8: 158 | J8: =SUMIF(order_item!B:B,A8,order_item!E:E) -> 158 | K8: =_xlfn.XLOOKUP(B8,customers!A:A,customers!D:D) -> Regular
A9: ORD6956059 | B9: CUST0128 | C9: Swiggy | D9: 45607 | E9: 0.45069444 | F9: Delivered | G9: 691 | H9: 0 | I9: 691 | J9: =SUMIF(order_item!B:B,A9,order_item!E:E) -> 691 | K9: =_xlfn.XLOOKUP(B9,customers!A:A,customers!D:D) -> Regular
A10: ORD4708297 | B10: CUST0266 | C10: Swiggy | D10: 45387 | E10: 0.86597222 | F10: Delivered | G10: 387 | H10: 0 | I10: 387 | J10: =SUMIF(order_item!B:B,A10,order_item!E:E) -> 387 | K10: =_xlfn.XLOOKUP(B10,customers!A:A,customers!D:D) -> Regular
A11: ORD3376915 | B11: CUST0426 | C11: Direct | D11: 45575 | E11: 0.67152778 | F11: Delivered | G11: 416 | H11: 41.6 | I11: 374.4 | J11: =SUMIF(order_item!B:B,A11,order_item!E:E) -> 416 | K11: =_xlfn.XLOOKUP(B11,customers!A:A,customers!D:D) -> Regular
A12: ORD2930810 | B12: CUST0023 | C12: Swiggy | D12: 45645 | E12: 0.67986111 | F12: Delivered | G12: 555 | H12: 55.5 | I12: 499.5 | J12: =SUMIF(order_item!B:B,A12,order_item!E:E) -> 555 | K12: =_xlfn.XLOOKUP(B12,customers!A:A,customers!D:D) -> Regular
A13: ORD7636771 | B13: CUST0328 | C13: Swiggy | D13: 45478 | E13: 0.71597222 | F13: Delivered | G13: 267 | H13: 0 | I13: 267 | J13: =SUMIF(order_item!B:B,A13,order_item!E:E) -> 267 | K13: =_xlfn.XLOOKUP(B13,customers!A:A,customers!D:D) -> Regular
... A1845: ORD2395263 | B1845: CUST0395 | C1845: Swiggy | D1845: 45414 | E1845: 0.44583333 | F1845: Delivered | G1845: 416 | H1845: 41.6 | I1845: 374.4 | J1845: =SUMIF(order_item!B:B,A1845,order_item!E:E) -> 416 | K1845: =_xlfn.XLOOKUP(B1845,customers!A:A,customers!D:D) -> Regular

Sheet Sheet7
A3: Row Labels | B3: Sum of item_total_price | C3: Sum of quantity
A4: Lemon Juice | B4: 10290 | C4: 210
A5: Veg Roll | B5: 13924 | C5: 236
A6: Virgin Mojito | B6: 17696 | C6: 224
A7: Blue Curacao Mojito | B7: 17775 | C7: 225
A8: Veg Sandwich | B8: 18091 | C8: 229
A9: Spring Roll | B9: 18285 | C9: 265
A10: Paneer Roll | B10: 18565 | C10: 235
A11: Mint Mojito | B11: 18723 | C11: 237
A12: Watermelon Mojito | B12: 22199 | C12: 281
A13: Veg Burger | B13: 24016 | C13: 304
A14: Paneer Burger | B14: 26878 | C14: 302
A15: Chicken Roll | B15: 27234 | C15: 306
... A32: Grand Total | B32: 966054 | C32: 8986

Sheet order_item
A1: order_item_id | B1: order_id | C1: item_id | D1: quantity | E1: item_total_price | F1: item_name | G1: CATEGORY | H1: PROFIT_PER_UNIT | I1: TOTAL_PROFIT
A2: OI000001 | B2: ORD6443037 | C2: ITM013 | D2: 3 | E2: 207 | F2: =_xlfn.XLOOKUP(C2,menu!A:A,menu!B:B) -> Spring Roll | G2: =_xlfn.XLOOKUP(C2,menu!A:A,menu!C:C) -> Rolls | H2: =_xlfn.XLOOKUP(C2,menu!A:A,menu!E:E) -> 21 | I2: =D2*H2 -> 63
A3: OI000002 | B3: ORD7387623 | C3: ITM015 | D3: 1 | E3: 149 | F3: =_xlfn.XLOOKUP(C3,menu!A:A,menu!B:B) -> Chicken Wings | G3: =_xlfn.XLOOKUP(C3,menu!A:A,menu!C:C) -> Starters | H3: =_xlfn.XLOOKUP(C3,menu!A:A,menu!E:E) -> 45 | I3: =D3*H3 -> 45
A4: OI000003 | B4: ORD7387623 | C4: ITM009 | D4: 1 | E4: 89 | F4: =_xlfn.XLOOKUP(C4,menu!A:A,menu!B:B) -> Paneer Burger | G4: =_xlfn.XLOOKUP(C4,menu!A:A,menu!C:C) -> Burger | H4: =_xlfn.XLOOKUP(C4,menu!A:A,menu!E:E) -> 27 | I4: =D4*H4 -> 27
A5: OI000004 | B5: ORD4280754 | C5: ITM009 | D5: 4 | E5: 356 | F5: =_xlfn.XLOOKUP(C5,menu!A:A,menu!B:B) -> Paneer Burger | G5: =_xlfn.XLOOKUP(C5,menu!A:A,menu!C:C) -> Burger | H5: =_xlfn.XLOOKUP(C5,menu!A:A,menu!E:E) -> 27 | I5: =D5*H5 -> 108
A6: OI000005 | B6: ORD3283789 | C6: ITM006 | D6: 1 | E6: 89 | F6: =_xlfn.XLOOKUP(C6,menu!A:A,menu!B:B) -> Paneer Momos | G6: =_xlfn.XLOOKUP(C6,menu!A:A,menu!C:C) -> Momos | H6: =_xlfn.XLOOKUP(C6,menu!A:A,menu!E:E) -> 27 | I6: =D6*H6 -> 27
A7: OI000006 | B7: ORD3283789 | C7: ITM026 | D7: 5 | E7: 395 | F7: =_xlfn.XLOOKUP(C7,menu!A:A,menu!B:B) -> Watermelon Mojito | G7: =_xlfn.XLOOKUP(C7,menu!A:A,menu!C:C) -> Beverages | H7: =_xlfn.XLOOKUP(C7,menu!A:A,menu!E:E) -> 24 | I7: =D7*H7 -> 120
A8: OI000007 | B8: ORD7309161 | C8: ITM004 | D8: 2 | E8: 158 | F8: =_xlfn.XLOOKUP(C8,menu!A:A,menu!B:B) -> Veg Momos | G8: =_xlfn.XLOOKUP(C8,menu!A:A,menu!C:C) -> Momos | H8: =_xlfn.XLOOKUP(C8,menu!A:A,menu!E:E) -> 24 | I8: =D8*H8 -> 48
A9: OI000008 | B9: ORD7309161 | C9: ITM017 | D9: 2 | E9: 298 | F9: =_xlfn.XLOOKUP(C9,menu!A:A,menu!B:B) -> Chicken Popcorn | G9: =_xlfn.XLOOKUP(C9,menu!A:A,menu!C:C) -> Starters | H9: =_xlfn.XLOOKUP(C9,menu!A:A,menu!E:E) -> 45 | I9: =D9*H9 -> 90
A10: OI000009 | B10: ORD7309161 | C10: ITM016 | D10: 2 | E10: 198 | F10: =_xlfn.XLOOKUP(C10,menu!A:A,menu!B:B) -> Veg Nuggets | G10: =_xlfn.XLOOKUP(C10,menu!A:A,menu!C:C) -> Starters | H10: =_xlfn.XLOOKUP(C10,menu!A:A,menu!E:E) -> 30 | I10: =D10*H10 -> 60
A11: OI000010 | B11: ORD7309161 | C11: ITM012 | D11: 4 | E11: 356 | F11: =_xlfn.XLOOKUP(C11,menu!A:A,menu!B:B) -> Chicken Roll | G11: =_xlfn.XLOOKUP(C11,menu!A:A,menu!C:C) -> Rolls | H11: =_xlfn.XLOOKUP(C11,menu!A:A,menu!E:E) -> 27 | I11: =D11*H11 -> 108
A12: OI000011 | B12: ORD7864256 | C12: ITM008 | D12: 1 | E12: 99 | F12: =_xlfn.XLOOKUP(C12,menu!A:A,menu!B:B) -> Chicken Burger | G12: =_xlfn.XLOOKUP(C12,menu!A:A,menu!C:C) -> Burger | H12: =_xlfn.XLOOKUP(C12,menu!A:A,menu!E:E) -> 30 | I12: =D12*H12 -> 30
A13: OI000012 | B13: ORD7864256 | C13: ITM009 | D13: 1 | E13: 89 | F13: =_xlfn.XLOOKUP(C13,menu!A:A,menu!B:B) -> Paneer Burger | G13: =_xlfn.XLOOKUP(C13,menu!A:A,menu!C:C) -> Burger | H13: =_xlfn.XLOOKUP(C13,menu!A:A,menu!E:E) -> 27 | I13: =D13*H13 -> 27
... A4586: OI004585 | B4586: ORD2395263 | C4586: ITM013 | D4586: 2 | E4586: 138 | F4586: =_xlfn.XLOOKUP(C4586,menu!A:A,menu!B:B) -> Spring Roll | G4586: =_xlfn.XLOOKUP(C4586,menu!A:A,menu!C:C) -> Rolls | H4586: =_xlfn.XLOOKUP(C4586,menu!A:A,menu!E:E) -> 21 | I4586: =D4586*H4586 -> 42

Sheet menu
A1: item_id | B1: item_name | C1: category | D1: price | E1: profit
A2: ITM001 | B2: Veg Sandwich | C2: Sandwich | D2: 79 | E2: =ROUND(D2*30%,0) -> 24
A3: ITM002 | B3: Paneer Sandwich | C3: Sandwich | D3: 99 | E3: =ROUND(D3*30%,0) -> 30
A4: ITM003 | B4: Chicken Sandwich | C4: Sandwich | D4: 119 | E4: =ROUND(D4*30%,0) -> 36
A5: ITM004 | B5: Veg Momos | C5: Momos | D5: 79 | E5: =ROUND(D5*30%,0) -> 24
A6: ITM005 | B6: Chicken Momos | C6: Momos | D6: 99 | E6: =ROUND(D6*30%,0) -> 30
A7: ITM006 | B7: Paneer Momos | C7: Momos | D7: 89 | E7: =ROUND(D7*30%,0) -> 27
A8: ITM007 | B8: Veg Burger | C8: Burger | D8: 79 | E8: =ROUND(D8*30%,0) -> 24
A9: ITM008 | B9: Chicken Burger | C9: Burger | D9: 99 | E9: =ROUND(D9*30%,0) -> 30
A10: ITM009 | B10: Paneer Burger | C10: Burger | D10: 89 | E10: =ROUND(D10*30%,0) -> 27
A11: ITM010 | B11: Veg Roll | C11: Rolls | D11: 59 | E11: =ROUND(D11*30%,0) -> 18
A12: ITM011 | B12: Paneer Roll | C12: Rolls | D12: 79 | E12: =ROUND(D12*30%,0) -> 24
A13: ITM012 | B13: Chicken Roll | C13: Rolls | D13: 89 | E13: =ROUND(D13*30%,0) -> 27
... A29: ITM028 | B29: Lemon Juice | C29: Beverages | D29: 49 | E29: =ROUND(D29*30%,0) -> 15

Sheet CUSTOMER_TYPE
A3: Row Labels | B3: Sum of final_amount | C3: Count of order_id | D3: AVERAGE ORDER VALUE
A4: New | B4: 226553.8 | C4: 474 | D4: =B4/C4 -> 477.9616
A5: Premium | B5: 122193.45 | C5: 276 | D5: =B5/C5 -> 442.72989
A6: Regular | B6: 520214.15 | C6: 1094 | D6: =B6/C6 -> 475.51568
A7: Grand Total | B7: 868961.4 | C7: 1844 | D7: =B7/C7 -> 471.2372

Sheet PIVOT_CATAGORY
A3: Row Labels | B3: Sum of item_total_price | C3: Sum of TOTAL_PROFIT
A4: Beverages | B4: 86683 | C4: 26358
A5: Burger | B5: 80990 | C5: 24570
A6: Momos | B6: 99406 | C6: 30159
A7: Rolls | B7: 78008 | C7: 23715
A8: Sandwich | B8: 75818 | C8: 22974
A9: Starters | B9: 545149 | C9: 164736
A10: Grand Total | B10: 966054 | C10: 292512

Sheet Channel Revenue
A3: Row Labels | B3: Sum of final_amount
A4: Direct | B4: 128857.3
A5: Swiggy | B5: 296898.8
A6: Zomato | B6: 443205.3
A7: Grand Total | B7: 868961.4

Sheet SUMMAEY
A1: METRIC | B1: VALUE
A2: TOTAL SALES | B2: =SUM(orders!G2:G1845) -> 966054 | D2: =B2-B3-B5+B4 -> 868961.4
A3: total DISCOUNT | B3: =SUM(orders!H2:H1845) -> 24533.85
A4: C O DISCOUNT | B4: =SUMIF(orders!F2:F1845,"Cancelled",orders!H2:H1845) -> 2055.25
A5: c o amouNT | B5: =SUMIF(orders!F2:F1845,"CANCELLED",orders!G2:G1845) -> 74614
A6: TOTAL SALES(FY 2024-25) | B6: =SUM(orders!I2:I1845) -> 868961.4
A7: TOTAL PROFIT | B7: =SUM(order_item!I2:I4586) -> 292512
A8: PROFIT MARGIN % | B8: =B7/B6*100 -> 33.662255
A9: TOTAL ORDERS | B9: =COUNTA(orders!A2:A1845) -> 1844
A10: AVERAGE ORDER VALUE | B10: =B6/B9 -> 471.2372
